dials_data/__init__.py
dials_data/cli.py
dials_data/datasets.py
dials_data/download.py
dials_data/py.typed
dials_data/pytest11.py
dials_data/definitions/4fluoro_cxi.yml
dials_data/definitions/MyD88_processed.yml
dials_data/definitions/Rigaku_HyPix_Arc.yml
dials_data/definitions/aluminium_standard.yml
dials_data/definitions/blend_tutorial.yml
dials_data/definitions/centroid_test_data.yml
dials_data/definitions/cspad_metrology.yml
dials_data/definitions/cunir_serial.yml
dials_data/definitions/cunir_serial_processed.yml
dials_data/definitions/dtpb_serial_processed.yml
dials_data/definitions/experiment_test_data.yml
dials_data/definitions/four_circle_eiger.yml
dials_data/definitions/fumarase.yml
dials_data/definitions/i04_weak_data.yml
dials_data/definitions/i19_1_pdteet_index.yml
dials_data/definitions/image_examples.yml
dials_data/definitions/indexing_test_data.yml
dials_data/definitions/insulin.yml
dials_data/definitions/insulin_processed.yml
dials_data/definitions/insulin_processed_xds_1.yml
dials_data/definitions/insulin_processed_xds_2.yml
dials_data/definitions/integration_test_data.yml
dials_data/definitions/isis_sxd_example_data.yml
dials_data/definitions/isis_sxd_nacl_processed.yml
dials_data/definitions/iterative_cspad_refinement.yml
dials_data/definitions/l_cysteine_4_sweeps_scaled.yml
dials_data/definitions/l_cysteine_dials_output.yml
dials_data/definitions/lcls_rayonix_kapton.yml
dials_data/definitions/lysozyme_JF16M_4img.yml
dials_data/definitions/lysozyme_JF16M_4img_spectra.yml
dials_data/definitions/lysozyme_electron_diffraction.yml
dials_data/definitions/lysozyme_ssx_25keV.yml
dials_data/definitions/misc_regression.yml
dials_data/definitions/mpro_x0305_processed.yml
dials_data/definitions/mpro_x0692.yml
dials_data/definitions/multi_crystal_proteinase_k.yml
dials_data/definitions/polyhedra_narrow_wedges.yml
dials_data/definitions/pycbf.yml
dials_data/definitions/pychef.yml
dials_data/definitions/quartz_processed.yml
dials_data-2.4.137.dist-info/licenses/LICENSE
dials_data-2.4.137.dist-info/METADATA
dials_data-2.4.137.dist-info/WHEEL
dials_data-2.4.137.dist-info/entry_points.txt
dials_data-2.4.137.dist-info/top_level.txt
dials_data-2.4.137.dist-info/RECORD
