Metadata-Version: 2.4
Name: dials_data
Version: 2.4.137
Summary: DIALS Regression Data Manager
Author-email: DIALS development team <dials-user-group@jiscmail.ac.uk>
License: BSD 3-Clause License
Project-URL: Homepage, https://github.com/dials/data
Project-URL: Bug Tracker, https://github.com/dials/data/issues
Project-URL: Documentation, https://dials-data.readthedocs.io/
Project-URL: Source Code, https://github.com/dials/data
Keywords: dials,dials_data
Classifier: Development Status :: 5 - Production/Stable
Classifier: Intended Audience :: Developers
Classifier: License :: OSI Approved :: BSD License
Classifier: Natural Language :: English
Classifier: Programming Language :: Python :: 3
Classifier: Programming Language :: Python :: 3.8
Classifier: Programming Language :: Python :: 3.9
Classifier: Programming Language :: Python :: 3.10
Classifier: Programming Language :: Python :: 3.11
Requires-Python: >=3.9
License-File: LICENSE
Requires-Dist: pyyaml
Requires-Dist: requests
Requires-Dist: py
Requires-Dist: importlib_resources~=6.3
Provides-Extra: test
Requires-Dist: coverage; extra == "test"
Requires-Dist: pytest; extra == "test"
Provides-Extra: doc
Requires-Dist: Sphinx~=6.2; extra == "doc"
Requires-Dist: sphinx_rtd_theme~=1.3; extra == "doc"
Dynamic: license-file
